{
  "id": "pl7",
  "type": "plotlines",
  "name": "Story Circle",
  "description": "A circular story structure",
  "version": "2021.1.28",
  "templateData": {
    "cards": [
      {
        "beatId": null,
        "bookId": null,
        "chapterId": 8,
        "characters": [],
        "description": [
          {
            "children": [
              {
                "text": "now capable of change"
              }
            ]
          }
        ],
        "id": 8,
        "imageId": null,
        "lineId": 1,
        "places": [],
        "position": 0,
        "seriesLineId": null,
        "tags": [],
        "templates": [],
        "title": "Change"
      },
      {
        "beatId": null,
        "bookId": null,
        "chapterId": 7,
        "characters": [],
        "description": [
          {
            "children": [
              {
                "text": "and go back to where they started"
              }
            ]
          }
        ],
        "id": 7,
        "imageId": null,
        "lineId": 1,
        "places": [],
        "position": 0,
        "seriesLineId": null,
        "tags": [],
        "templates": [],
        "title": "Return"
      },
      {
        "beatId": null,
        "bookId": null,
        "chapterId": 6,
        "characters": [],
        "description": [
          {
            "children": [
              {
                "text": "pay its price"
              }
            ]
          }
        ],
        "id": 6,
        "imageId": null,
        "lineId": 1,
        "places": [],
        "position": 0,
        "seriesLineId": null,
        "tags": [],
        "templates": [],
        "title": "Take"
      },
      {
        "beatId": null,
        "bookId": null,
        "chapterId": 5,
        "characters": [],
        "description": [
          {
            "children": [
              {
                "text": "find what they wanted"
              }
            ]
          }
        ],
        "id": 5,
        "imageId": null,
        "lineId": 1,
        "places": [],
        "position": 0,
        "seriesLineId": null,
        "tags": [],
        "templates": [],
        "title": "Find"
      },
      {
        "beatId": null,
        "bookId": null,
        "chapterId": 4,
        "characters": [],
        "description": [
          {
            "children": [
              {
                "text": "adapt to it"
              }
            ]
          }
        ],
        "id": 4,
        "imageId": null,
        "lineId": 1,
        "places": [],
        "position": 0,
        "seriesLineId": null,
        "tags": [],
        "templates": [],
        "title": "Search"
      },
      {
        "beatId": null,
        "bookId": null,
        "chapterId": 3,
        "characters": [],
        "description": [
          {
            "children": [
              {
                "text": "they enter an unfamiliar situation"
              }
            ]
          }
        ],
        "id": 3,
        "imageId": null,
        "lineId": 1,
        "places": [],
        "position": 0,
        "seriesLineId": null,
        "tags": [],
        "templates": [],
        "title": "Go"
      },
      {
        "beatId": null,
        "bookId": null,
        "chapterId": 2,
        "characters": [],
        "description": [
          {
            "children": [
              {
                "text": "but they want something"
              }
            ]
          }
        ],
        "id": 2,
        "imageId": null,
        "lineId": 1,
        "places": [],
        "position": 0,
        "seriesLineId": null,
        "tags": [],
        "templates": [],
        "title": "Need"
      },
      {
        "beatId": null,
        "bookId": null,
        "chapterId": 1,
        "characters": [],
        "description": [
          {
            "children": [
              {
                "text": "A character is in a zone of comfort"
              }
            ]
          }
        ],
        "id": 1,
        "imageId": null,
        "lineId": 1,
        "places": [],
        "position": 0,
        "seriesLineId": null,
        "tags": [],
        "templates": [],
        "title": "You"
      }
    ],
    "chapters": [
      {
        "bookId": 1,
        "id": 8,
        "position": 7,
        "templates": [],
        "time": 0,
        "title": "auto"
      },
      {
        "bookId": 1,
        "id": 7,
        "position": 6,
        "templates": [],
        "time": 0,
        "title": "auto"
      },
      {
        "bookId": 1,
        "id": 6,
        "position": 5,
        "templates": [],
        "time": 0,
        "title": "auto"
      },
      {
        "bookId": 1,
        "id": 5,
        "position": 4,
        "templates": [],
        "time": 0,
        "title": "auto"
      },
      {
        "bookId": 1,
        "id": 4,
        "position": 3,
        "templates": [],
        "time": 0,
        "title": "auto"
      },
      {
        "bookId": 1,
        "id": 3,
        "position": 2,
        "templates": [],
        "time": 0,
        "title": "auto"
      },
      {
        "bookId": 1,
        "id": 2,
        "position": 1,
        "templates": [],
        "time": 0,
        "title": "auto"
      },
      {
        "bookId": 1,
        "id": 1,
        "position": 0,
        "templates": [],
        "time": 0,
        "title": "auto"
      }
    ]
  }
}
